<cartoonnetwork>
	<response status="SUCCESS"/>
	<game id="4917135" rating="0" difficulty="0" status="1">
		<thumbnail>
			http://i.cdn.turner.com/v5cache/CARTOON/gamecreator/images/Blue/Don/Charger/4917135.jpg
		</thumbnail>
		<title>Steel Smash Nitro</title>
		<creator>/Blue/Don/Charger/</creator>
		<timesPlayed>0</timesPlayed>
	</game>
	<game id="4917143" rating="0" difficulty="0" status="1">
		<thumbnail>
			http://i.cdn.turner.com/v5cache/CARTOON/gamecreator/images/Awesome/Val/Aurora/4917143.jpg
		</thumbnail>
		<title>Atomic Shadow Rumble</title>
		<creator>/Awesome/Val/Aurora/</creator>
		<timesPlayed>1</timesPlayed>
	</game>
	<game id="4917155" rating="0" difficulty="0" status="1">
		<thumbnail>
			http://i.cdn.turner.com/v5cache/CARTOON/gamecreator/images/Tricky/Jake/Cobra/4917155.jpg
		</thumbnail>
		<title>Storm Power Thunder</title>
		<creator>/Tricky/Jake/Cobra/</creator>
		<timesPlayed>0</timesPlayed>
	</game>
	<game id="4917122" rating="0" difficulty="0" status="1">
		<thumbnail>
			http://i.cdn.turner.com/v5cache/CARTOON/gamecreator/images/Royal/Iris/Rutabaga/4917122.jpg
		</thumbnail>
		<title>Rock Shadow Attack</title>
		<creator>/Royal/Iris/Rutabaga/</creator>
		<timesPlayed>0</timesPlayed>
	</game>
	<game id="4917124" rating="0" difficulty="0" status="1">
		<thumbnail>
			http://i.cdn.turner.com/v5cache/CARTOON/gamecreator/images/Graceful/Kyle/Pirate/4917124.jpg
		</thumbnail>
		<title>Jetray Jetray Turbo</title>
		<creator>/Graceful/Kyle/Pirate/</creator>
		<timesPlayed>0</timesPlayed>
	</game>
	<game id="4917116" rating="0" difficulty="0" status="1">
		<thumbnail>
			http://i.cdn.turner.com/v5cache/CARTOON/gamecreator/images/Dashing/Isaiah/Werewolf/4917116.jpg
		</thumbnail>
		<title>Shadow Force Galaxy</title>
		<creator>/Dashing/Isaiah/Werewolf/</creator>
		<timesPlayed>0</timesPlayed>
	</game>
	<game id="4917104" rating="0" difficulty="0" status="1">
		<thumbnail>
			http://i.cdn.turner.com/v5cache/CARTOON/gamecreator/images/Charming/Clark/Zigzag/4917104.jpg
		</thumbnail>
		<title>Invasion Quake Storm</title>
		<creator>/Charming/Clark/Zigzag/</creator>
		<timesPlayed>1</timesPlayed>
	</game>
	<game id="4917107" rating="0" difficulty="0" status="1">
		<thumbnail>
			http://i.cdn.turner.com/v5cache/CARTOON/gamecreator/images/Absurd/Ace/Aardvark/4917107.jpg
		</thumbnail>
		<title>Sonic Nova Rumble</title>
		<creator>/Absurd/Ace/Aardvark/</creator>
		<timesPlayed>5</timesPlayed>
	</game>
	<game id="4917098" rating="0" difficulty="0" status="1">
		<thumbnail>
			http://i.cdn.turner.com/v5cache/CARTOON/gamecreator/images/Odd/Duke/Buzzard/4917098.jpg
		</thumbnail>
		<title>Power Danger Atomic</title>
		<creator>/Odd/Duke/Buzzard/</creator>
		<timesPlayed>0</timesPlayed>
	</game>
	<game id="4917112" rating="0" difficulty="0" status="1">
		<thumbnail>
			http://i.cdn.turner.com/v5cache/CARTOON/gamecreator/images/Radiant/Daisy/Walrus/4917112.jpg
		</thumbnail>
		<title>Space Turbo Target</title>
		<creator>/Radiant/Daisy/Walrus/</creator>
		<timesPlayed>0</timesPlayed>
	</game>
</cartoonnetwork>
