<cartoonnetwork>
	<response status="SUCCESS"/>
	<game id="4916703" rating="0" difficulty="0" status="1">
		<thumbnail>
			http://i.cdn.turner.com/v5cache/CARTOON/gamecreator/images/Sneaky/Zelda/Acrobat/4916703.jpg
		</thumbnail>
		<title>Titan Star Iron</title>
		<creator>/Sneaky/Zelda/Acrobat/</creator>
		<timesPlayed>0</timesPlayed>
	</game>
	<game id="4916707" rating="0" difficulty="0" status="1">
		<thumbnail>
			http://i.cdn.turner.com/v5cache/CARTOON/gamecreator/images/Lucky/Ginger/Crash/4916707.jpg
		</thumbnail>
		<title>Battle Mission Warrior</title>
		<creator>/Lucky/Ginger/Crash/</creator>
		<timesPlayed>0</timesPlayed>
	</game>
	<game id="4916670" rating="0" difficulty="0" status="1">
		<thumbnail>
			http://i.cdn.turner.com/v5cache/CARTOON/gamecreator/images/Mirthful/Peter/Blade/4916670.jpg
		</thumbnail>
		<title>Lightning Jetray Power</title>
		<creator>/Mirthful/Peter/Blade/</creator>
		<timesPlayed>0</timesPlayed>
	</game>
	<game id="4916635" rating="0" difficulty="0" status="1">
		<thumbnail>
			http://i.cdn.turner.com/v5cache/CARTOON/gamecreator/images/Leaping/Nick/Turtle/4916635.jpg
		</thumbnail>
		<title>Atomic Mission Rock</title>
		<creator>/Leaping/Nick/Turtle/</creator>
		<timesPlayed>1</timesPlayed>
	</game>
	<game id="4916642" rating="0" difficulty="0" status="1">
		<thumbnail>
			http://i.cdn.turner.com/v5cache/CARTOON/gamecreator/images/Beastly/Dewey/Nova/4916642.jpg
		</thumbnail>
		<title>Rocket Cosmic Clash</title>
		<creator>/Beastly/Dewey/Nova/</creator>
		<timesPlayed>1</timesPlayed>
	</game>
	<game id="4916665" rating="0" difficulty="0" status="1">
		<thumbnail>
			http://i.cdn.turner.com/v5cache/CARTOON/gamecreator/images/Husky/Ray/Catapult/4916665.jpg
		</thumbnail>
		<title>Shadow Plasma Assault</title>
		<creator>/Husky/Ray/Catapult/</creator>
		<timesPlayed>2</timesPlayed>
	</game>
	<game id="4916648" rating="0" difficulty="0" status="1">
		<thumbnail>
			http://i.cdn.turner.com/v5cache/CARTOON/gamecreator/images/Scary/Carlos/Cyclone/4916648.jpg
		</thumbnail>
		<title>Jetray Sonic Challenge</title>
		<creator>/Scary/Carlos/Cyclone/</creator>
		<timesPlayed>0</timesPlayed>
	</game>
	<game id="4916607" rating="0" difficulty="0" status="1">
		<thumbnail>
			http://i.cdn.turner.com/v5cache/CARTOON/gamecreator/images/Lucky/Aaron/Parallax/4916607.jpg
		</thumbnail>
		<title>Fusion Galaxy Hero</title>
		<creator>/Lucky/Aaron/Parallax/</creator>
		<timesPlayed>0</timesPlayed>
	</game>
	<game id="4916625" rating="0" difficulty="0" status="1">
		<thumbnail>
			http://i.cdn.turner.com/v5cache/CARTOON/gamecreator/images/Awful/William/Unicycle/4916625.jpg
		</thumbnail>
		<title>Escape Alien Invasion</title>
		<creator>/Awful/William/Unicycle/</creator>
		<timesPlayed>0</timesPlayed>
	</game>
	<game id="4916604" rating="0" difficulty="0" status="1">
		<thumbnail>
			http://i.cdn.turner.com/v5cache/CARTOON/gamecreator/images/Weird/Carlos/Goblin/4916604.jpg
		</thumbnail>
		<title>Solar Cosmic Nano</title>
		<creator>/Weird/Carlos/Goblin/</creator>
		<timesPlayed>0</timesPlayed>
	</game>
</cartoonnetwork>
