<?xml version='1.0' encoding='utf-8'?>
<cartoonnetwork>
	<response status="SUCCESS" />
	<game id="17560228" rating="0" difficulty="0" status="0" timeToBeat="0" createDate="09/20/2012">
		<thumbnail>/gamecreators/images2/Crunchy/Ava/Blizzard/17560228.jpg</thumbnail>
		<title>Rocket Animo Droid</title>
		<creator>Crunchy Ava Blizzard</creator>
		<relatedgames />
	</game>
	<game id="10952581" rating="0" difficulty="0" status="0" timeToBeat="0" createDate="09/21/2009">
		<thumbnail>/gamecreators/images2/Gloomy/Harry/Bolt/10952581.jpg</thumbnail>
		<title>Danger Vilgax Fusion</title>
		<creator>Gloomy Harry Bolt</creator>
		<relatedgames />
	</game>
	<game id="17423219" rating="0" difficulty="0" status="0" timeToBeat="0" createDate="09/17/2012">
		<thumbnail>/gamecreators/images2/Quiet/Hunter/Blob/17423219.jpg</thumbnail>
		<title>Turbo Champion Adventure</title>
		<creator>Quiet Hunter Blob</creator>
		<relatedgames />
	</game>
	<game id="10057344" rating="0" difficulty="0" status="0">
		<thumbnail>/gamecreators/images/Crispy/Michael/Dynamite/10057344.jpg</thumbnail>
		<title>Ultimate Fire Force</title>
		<creator>Crispy Michael Dynamite</creator>
		<relatedgames />
	</game>
	<game id="10927920" rating="0" difficulty="0" status="0" timeToBeat="0" createDate="09/19/2009">
		<thumbnail>/gamecreators/images2/Valiant/Tom/Paradox/10927920.jpg</thumbnail>
		<title>Light Assault Danger</title>
		<creator>Valiant Tom Paradox</creator>
		<relatedgames />
	</game>
	<game id="17178491" rating="0" difficulty="0" status="0" timeToBeat="0" createDate="07/01/2012">
		<thumbnail>/gamecreators/images2/Extreme/Alan/Avocado/17178491.jpg</thumbnail>
		<title>Chase Steel Thunder</title>
		<creator>Extreme Alan Avocado</creator>
		<relatedgames />
	</game>
	<game id="10918078" rating="0" difficulty="0" status="0" timeToBeat="0" createDate="09/18/2009">
		<thumbnail>/gamecreators/images2/Daring/Will/Safari/10918078.jpg</thumbnail>
		<title>Solar Dark Fire</title>
		<creator>Daring Will Safari</creator>
		<relatedgames />
	</game>
	<game id="10706482" rating="0" difficulty="0" status="0" timeToBeat="0" createDate="08/23/2009">
		<thumbnail>/gamecreators/images2/Green/Cody/Fathom/10706482.jpg</thumbnail>
		<title>Atomic Swampfire Mission</title>
		<creator>Green Cody Fathom</creator>
		<relatedgames />
	</game>
	<game id="10918670" rating="0" difficulty="0" status="0" timeToBeat="0" createDate="09/18/2009">
		<thumbnail>/gamecreators/images2/Sneaky/Bubba/Kumquat/10918670.jpg</thumbnail>
		<title>Cosmic Steel Warrior</title>
		<creator>Sneaky Bubba Kumquat</creator>
		<relatedgames />
	</game>
	<game id="10706022" rating="0" difficulty="0" status="0" timeToBeat="0" createDate="08/23/2009">
		<thumbnail>/gamecreators/images2/Red/Hunter/Slurp/10706022.jpg</thumbnail>
		<title>Target Rock Droid</title>
		<creator>Red Hunter Slurp</creator>
		<relatedgames />
	</game>
</cartoonnetwork>