<?xml version='1.0' encoding='utf-8'?>
<cartoonnetwork>
	<response status="SUCCESS" />
	<game id="10039147" rating="0" difficulty="0" status="0">
		<thumbnail>/gamecreators/images/Husky/Bessie/Iceberg/10039147.jpg</thumbnail>
		<title>Shadow Attack Galaxy</title>
		<creator>Husky Bessie Iceberg</creator>
		<relatedgames />
	</game>
	<game id="10057344" rating="0" difficulty="0" status="0">
		<thumbnail>/gamecreators/images/Crispy/Michael/Dynamite/10057344.jpg</thumbnail>
		<title>Ultimate Fire Force</title>
		<creator>Crispy Michael Dynamite</creator>
		<relatedgames />
	</game>
	<game id="17383215" rating="0" difficulty="0" status="0" timeToBeat="0" createDate="08/31/2012">
		<thumbnail>/gamecreators/images2/Ironic/DJ/Giraffe/17383215.jpg</thumbnail>
		<title>Force Techno Blaster</title>
		<creator>Ironic DJ Giraffe</creator>
		<relatedgames />
	</game>
	<game id="17316341" rating="0" difficulty="0" status="0" timeToBeat="0" createDate="08/08/2012">
		<thumbnail>/gamecreators/images2/Queen/Rich/Sunshine/17316341.jpg</thumbnail>
		<title>Galaxy Danger Challenge</title>
		<creator>Queen Rich Sunshine</creator>
		<relatedgames />
	</game>
	<game id="10916687" rating="0" difficulty="0" status="0" timeToBeat="0" createDate="09/18/2009">
		<thumbnail>/gamecreators/images2/Tricky/Felix/Pontoon/10916687.jpg</thumbnail>
		<title>Alien Metal Rock</title>
		<creator>Tricky Felix Pontoon</creator>
		<relatedgames />
	</game>
	<game id="10946286" rating="0" difficulty="0" status="0" timeToBeat="0" createDate="09/20/2009">
		<thumbnail>/gamecreators/images2/Adorable/Benjamin/Robot/10946286.jpg</thumbnail>
		<title>Fire Fire Robot</title>
		<creator>Adorable Benjamin Robot</creator>
		<relatedgames />
	</game>
	<game id="17574657" rating="0" difficulty="0" status="0" timeToBeat="0" createDate="09/21/2012">
		<thumbnail>/gamecreators/images2/Creepy/George/Sprinkle/17574657.jpg</thumbnail>
		<title>Chill Plumber Vilgax</title>
		<creator>Creepy George Sprinkle</creator>
		<relatedgames />
	</game>
	<game id="10931323" rating="0" difficulty="0" status="0" timeToBeat="0" createDate="09/19/2009">
		<thumbnail>/gamecreators/images2/Gigantic/Jose/Dynamite/10931323.jpg</thumbnail>
		<title>Fire Thunder Storm</title>
		<creator>Gigantic Jose Dynamite</creator>
		<relatedgames />
	</game>
	<game id="17259079" rating="0" difficulty="0" status="0" timeToBeat="0" createDate="07/24/2012">
		<thumbnail>/gamecreators/images2/Queen/Lawrence/Eggplant/17259079.jpg</thumbnail>
		<title>Cosmic Iron Chill</title>
		<creator>Queen Lawrence Eggplant</creator>
		<relatedgames />
	</game>
	<game id="17404209" rating="0" difficulty="0" status="0" timeToBeat="0" createDate="09/09/2012">
		<thumbnail>/gamecreators/images2/Zany/Luke/Stampede/17404209.jpg</thumbnail>
		<title>Pulse Adventure Shadow</title>
		<creator>Zany Luke Stampede</creator>
		<relatedgames />
	</game>
</cartoonnetwork>