<?xml version='1.0' encoding='utf-8'?>
<cartoonnetwork>
	<response status="SUCCESS" />
	<game id="17301462" rating="0" difficulty="0" status="0" timeToBeat="0" createDate="08/04/2012">
		<thumbnail>/gamecreators/images2/Ironic/Isaac/Deadbolt/17301462.jpg</thumbnail>
		<title>Thunder Ultra Alien</title>
		<creator>Ironic Isaac Deadbolt</creator>
		<relatedgames />
	</game>
	<game id="17223727" rating="0" difficulty="0" status="0" timeToBeat="0" createDate="07/14/2012">
		<thumbnail>/gamecreators/images2/Quick/Chuck/Cobweb/17223727.jpg</thumbnail>
		<title>Power Adventure Champion</title>
		<creator>Quick Chuck Cobweb</creator>
		<relatedgames />
	</game>
	<game id="10042807" rating="0" difficulty="0" status="0">
		<thumbnail>/gamecreators/images/Noisy/Gretel/Gumbo/10042807.jpg</thumbnail>
		<title>Adventure Lightning Mega</title>
		<creator>Noisy Gretel Gumbo</creator>
		<relatedgames />
	</game>
	<game id="10924392" rating="0" difficulty="0" status="0" timeToBeat="0" createDate="09/19/2009">
		<thumbnail>/gamecreators/images2/Adorable/Eddie/Catapult/10924392.jpg</thumbnail>
		<title>Fury Fusion Crusher</title>
		<creator>Adorable Eddie Catapult</creator>
		<relatedgames />
	</game>
	<game id="10937036" rating="0" difficulty="0" status="0" timeToBeat="0" createDate="09/20/2009">
		<thumbnail>/gamecreators/images2/Red/Laura/Jungle/10937036.jpg</thumbnail>
		<title>Ultra Mega Fire</title>
		<creator>Red Laura Jungle</creator>
		<relatedgames />
	</game>
	<game id="10926594" rating="0" difficulty="0" status="0" timeToBeat="0" createDate="09/19/2009">
		<thumbnail>/gamecreators/images2/Valiant/Maya/Rutabaga/10926594.jpg</thumbnail>
		<title>Light Search Ultra</title>
		<creator>Valiant Maya Rutabaga</creator>
		<relatedgames />
	</game>
	<game id="17333051" rating="0" difficulty="0" status="0" timeToBeat="0" createDate="08/12/2012">
		<thumbnail>/gamecreators/images2/Daring/Ricardo/Tiger/17333051.jpg</thumbnail>
		<title>Chill Dark Sonic</title>
		<creator>Daring Ricardo Tiger</creator>
		<relatedgames />
	</game>
	<game id="17585367" rating="0" difficulty="0" status="0" timeToBeat="0" createDate="09/21/2012">
		<thumbnail>/gamecreators/images2/Keen/Isaiah/Phoenix/17585367.jpg</thumbnail>
		<title>Energy Giga Dark</title>
		<creator>Keen Isaiah Phoenix</creator>
		<relatedgames />
	</game>
	<game id="10919825" rating="0" difficulty="0" status="0" timeToBeat="0" createDate="09/18/2009">
		<thumbnail>/gamecreators/images2/Red/Bruce/Ooze/10919825.jpg</thumbnail>
		<title>Space Turbo Solar</title>
		<creator>Red Bruce Ooze</creator>
		<relatedgames />
	</game>
	<game id="17281265" rating="0" difficulty="0" status="0" timeToBeat="0" createDate="07/30/2012">
		<thumbnail>/gamecreators/images2/Amazing/Alvin/Thing/17281265.jpg</thumbnail>
		<title>Warrior Spike Mega</title>
		<creator>Amazing Alvin Thing</creator>
		<relatedgames />
	</game>
</cartoonnetwork>