<cartoonnetwork>
	<response status="SUCCESS"/>
	<game id="10942111" rating="0" difficulty="0" status="0" timeToBeat="0" createDate="09/20/2009">
		<thumbnail>
			http://i.cdn.turner.com/v5cache/CARTOON/gamecreator/images2/Fragrant/Cynthia/Ladybug/10942111.jpg
		</thumbnail>
		<title>Nano Target Universe</title>
		<creator>Fragrant Cynthia Ladybug</creator>
		<relatedgames/>
	</game>
	<game id="17348799" rating="0" difficulty="0" status="0" timeToBeat="0" createDate="08/18/2012">
		<thumbnail>
			http://i.cdn.turner.com/v5cache/CARTOON/gamecreator/images2/Loyal/Helen/Blammo/17348799.jpg
		</thumbnail>
		<title>Rock Vilgax Solar</title>
		<creator>Loyal Helen Blammo</creator>
		<relatedgames/>
	</game>
	<game id="17076960" rating="0" difficulty="0" status="0" timeToBeat="0" createDate="05/31/2012">
		<thumbnail>
			http://i.cdn.turner.com/v5cache/CARTOON/gamecreator/images2/Bold/Bobby/Yoyo/17076960.jpg
		</thumbnail>
		<title>Pulse Gear Nova</title>
		<creator>Bold Bobby Yoyo</creator>
		<relatedgames/>
	</game>
	<game id="17420513" rating="0" difficulty="0" status="0" timeToBeat="0" createDate="09/16/2012">
		<thumbnail>
			http://i.cdn.turner.com/v5cache/CARTOON/gamecreator/images2/Hyper/Silvia/Pulse/17420513.jpg
		</thumbnail>
		<title>Adventure Star Spike</title>
		<creator>Hyper Silvia Pulse</creator>
		<relatedgames/>
	</game>
	<game id="17355672" rating="0" difficulty="0" status="0" timeToBeat="0" createDate="08/20/2012">
		<thumbnail>
			http://i.cdn.turner.com/v5cache/CARTOON/gamecreator/images2/Purple/Rosetta/Rebel/17355672.jpg
		</thumbnail>
		<title>Smash Power Earth</title>
		<creator>Purple Rosetta Rebel</creator>
		<relatedgames/>
	</game>
	<game id="17285375" rating="0" difficulty="0" status="0" timeToBeat="0" createDate="07/31/2012">
		<thumbnail>
			http://i.cdn.turner.com/v5cache/CARTOON/gamecreator/images2/Negative/Andy/Atlas/17285375.jpg
		</thumbnail>
		<title>Water Blaster Challenge</title>
		<creator>Negative Andy Atlas</creator>
		<relatedgames/>
	</game>
	<game id="17400901" rating="0" difficulty="0" status="0" timeToBeat="0" createDate="09/08/2012">
		<thumbnail>
			http://i.cdn.turner.com/v5cache/CARTOON/gamecreator/images2/Flying/Riley/17400901.jpg
		</thumbnail>
		<title>Shadow Clash Atomic</title>
		<creator>Flying Riley</creator>
		<relatedgames/>
	</game>
	<game id="10038161" rating="0" difficulty="0" status="0">
		<thumbnail>
			http://i.cdn.turner.com/v5cache/CARTOON/gamecreator/images/Dynamic/Matt/Aardvark/10038161.jpg
		</thumbnail>
		<title>Warrior Ultra Laser</title>
		<creator>Dynamic Matt Aardvark</creator>
		<relatedgames/>
	</game>
	<game id="17357894" rating="0" difficulty="0" status="0" timeToBeat="0" createDate="08/21/2012">
		<thumbnail>
			http://i.cdn.turner.com/v5cache/CARTOON/gamecreator/images2/Stormy/Wes/Steel/17357894.jpg
		</thumbnail>
		<title>Racer Defense Plasma</title>
		<creator>Stormy Wes Steel</creator>
		<relatedgames/>
	</game>
	<game id="17269325" rating="0" difficulty="0" status="0" timeToBeat="0" createDate="07/27/2012">
		<thumbnail>
			http://i.cdn.turner.com/v5cache/CARTOON/gamecreator/images2/Seismic/Bert/Mercury/17269325.jpg
		</thumbnail>
		<title>Star Plumber Thunder</title>
		<creator>Seismic Bert Mercury</creator>
		<relatedgames/>
	</game>
</cartoonnetwork>