<?xml version='1.0' encoding='utf-8'?>
<cartoonnetwork>
	<response status="SUCCESS" />
	<game id="10926778" rating="0" difficulty="0" status="0" timeToBeat="0" createDate="09/19/2009">
		<thumbnail>/gamecreators/images2/Shaggy/Brett/Shark/10926778.jpg</thumbnail>
		<title>Doom Atomic Razor</title>
		<creator>Shaggy Brett Shark</creator>
		<relatedgames />
	</game>
	<game id="10953624" rating="0" difficulty="0" status="0" timeToBeat="0" createDate="09/21/2009">
		<thumbnail>/gamecreators/images2/Witty/Madison/Squish/10953624.jpg</thumbnail>
		<title>Power Spike Hyper</title>
		<creator>Witty Madison Squish</creator>
		<relatedgames />
	</game>
	<game id="16860071" rating="0" difficulty="0" status="0" timeToBeat="0" createDate="03/30/2012">
		<thumbnail>/gamecreators/images2/Flying/Nicholas/Rumble/16860071.jpg</thumbnail>
		<title>Battle Spark Force</title>
		<creator>Flying Nicholas Rumble</creator>
		<relatedgames />
	</game>
	<game id="10068760" rating="0" difficulty="0" status="0">
		<thumbnail>/gamecreators/images/Dynamic/Leopold/Wizard/10068760.jpg</thumbnail>
		<title>Swampfire Mega Battle</title>
		<creator>Dynamic Leopold Wizard</creator>
		<relatedgames />
	</game>
	<game id="10045421" rating="0" difficulty="0" status="0">
		<thumbnail>/gamecreators/images/Nomadic/Augustus/Nacho/10045421.jpg</thumbnail>
		<title>Solar Rocket Atomic</title>
		<creator>Nomadic Augustus Nacho</creator>
		<relatedgames />
	</game>
	<game id="17540459" rating="0" difficulty="0" status="0" timeToBeat="0" createDate="09/20/2012">
		<thumbnail>/gamecreators/images2/Agile/Drake/Glop/17540459.jpg</thumbnail>
		<title>Rock Racer Force</title>
		<creator>Agile Drake Glop</creator>
		<relatedgames />
	</game>
	<game id="17188315" rating="0" difficulty="0" status="0" timeToBeat="0" createDate="07/04/2012">
		<thumbnail>/gamecreators/images2/Crispy/Steven/Bazooka/17188315.jpg</thumbnail>
		<title>Shock Echo Adventure</title>
		<creator>Crispy Steven Bazooka</creator>
		<relatedgames />
	</game>
	<game id="17210717" rating="0" difficulty="0" status="0" timeToBeat="0" createDate="07/11/2012">
		<thumbnail>/gamecreators/images2/Vast/Jack/Creature/17210717.jpg</thumbnail>
		<title>Metal Iron Defense</title>
		<creator>Vast Jack Creature</creator>
		<relatedgames />
	</game>
	<game id="10065549" rating="0" difficulty="0" status="0">
		<thumbnail>/gamecreators/images/Brave/Tabitha/Cupcake/10065549.jpg</thumbnail>
		<title>Alien Swampfire Star</title>
		<creator>Brave Tabitha Cupcake</creator>
		<relatedgames />
	</game>
	<game id="17301462" rating="0" difficulty="0" status="0" timeToBeat="0" createDate="08/04/2012">
		<thumbnail>/gamecreators/images2/Ironic/Isaac/Deadbolt/17301462.jpg</thumbnail>
		<title>Thunder Ultra Alien</title>
		<creator>Ironic Isaac Deadbolt</creator>
		<relatedgames />
	</game>
</cartoonnetwork>