<?xml version='1.0' encoding='utf-8'?>
<cartoonnetwork>
	<response status="SUCCESS" />
	<game id="10952658" rating="0" difficulty="0" status="0" timeToBeat="0" createDate="09/21/2009">
		<thumbnail>/gamecreators/images2/Visible/Zachary/Scribble/10952658.jpg</thumbnail>
		<title>Hex Assault Drone</title>
		<creator>Visible Zachary Scribble</creator>
		<relatedgames />
	</game>
	<game id="10934959" rating="0" difficulty="0" status="0" timeToBeat="0" createDate="09/19/2009">
		<thumbnail>/gamecreators/images2/Peculiar/Derek/Blubber/10934959.jpg</thumbnail>
		<title>Ben Sonic Hero</title>
		<creator>Peculiar Derek Blubber</creator>
		<relatedgames />
	</game>
	<game id="17417687" rating="0" difficulty="0" status="0" timeToBeat="0" createDate="09/15/2012">
		<thumbnail>/gamecreators/images2/Stormy/Mordecai/Vulture/17417687.jpg</thumbnail>
		<title>Invasion Ultra Lightning</title>
		<creator>Stormy Mordecai Vulture</creator>
		<relatedgames />
	</game>
	<game id="17310250" rating="0" difficulty="0" status="0" timeToBeat="0" createDate="08/06/2012">
		<thumbnail>/gamecreators/images2/Defiant/Mario/Blob/17310250.jpg</thumbnail>
		<title>Chase Thunder Droid</title>
		<creator>Defiant Mario Blob</creator>
		<relatedgames />
	</game>
	<game id="10923368" rating="0" difficulty="0" status="0" timeToBeat="0" createDate="09/19/2009">
		<thumbnail>/gamecreators/images2/Wise/Herman/Tornado/10923368.jpg</thumbnail>
		<title>Blaster Force Clash</title>
		<creator>Wise Herman Tornado</creator>
		<relatedgames />
	</game>
	<game id="10919466" rating="0" difficulty="0" status="0" timeToBeat="0" createDate="09/18/2009">
		<thumbnail>/gamecreators/images2/Cheerful/Blake/Crater/10919466.jpg</thumbnail>
		<title>Clash Atomic Stone</title>
		<creator>Cheerful Blake Crater</creator>
		<relatedgames />
	</game>
	<game id="10919184" rating="0" difficulty="0" status="0" timeToBeat="0" createDate="09/18/2009">
		<thumbnail>/gamecreators/images2/Fizzy/Laura/Tugboat/10919184.jpg</thumbnail>
		<title>Siege Atomic Rush</title>
		<creator>Fizzy Laura Tugboat</creator>
		<relatedgames />
	</game>
	<game id="17324743" rating="0" difficulty="0" status="0" timeToBeat="0" createDate="08/10/2012">
		<thumbnail>/gamecreators/images2/Loopy/Autumn/Snorkel/17324743.jpg</thumbnail>
		<title>Alien Pulse Universe</title>
		<creator>Loopy Autumn Snorkel</creator>
		<relatedgames />
	</game>
	<game id="10953680" rating="0" difficulty="0" status="0" timeToBeat="0" createDate="09/21/2009">
		<thumbnail>/gamecreators/images2/Orange/Sara/Cyborg/10953680.jpg</thumbnail>
		<title>Hero Robot Shock</title>
		<creator>Orange Sara Cyborg</creator>
		<relatedgames />
	</game>
	<game id="17409654" rating="0" difficulty="0" status="0" timeToBeat="0" createDate="09/12/2012">
		<thumbnail>/gamecreators/images2/Magnetic/Lucas/Mars/17409654.jpg</thumbnail>
		<title>Assault Titan Laser</title>
		<creator>Magnetic Lucas Mars</creator>
		<relatedgames />
	</game>
</cartoonnetwork>