<?xml version='1.0' encoding='utf-8'?>
<cartoonnetwork>
	<response status="SUCCESS" />
	<game id="10028568" rating="0" difficulty="0" status="0">
		<thumbnail>/gamecreators/images/Atomic/Harvey/Aardvark/10028568.jpg</thumbnail>
		<title>Fire Spike Search</title>
		<creator>Atomic Harvey Aardvark</creator>
		<relatedgames />
	</game>
	<game id="10928370" rating="0" difficulty="0" status="0" timeToBeat="0" createDate="09/19/2009">
		<thumbnail>/gamecreators/images2/Handsome/Jeffrey/Aardvark/10928370.jpg</thumbnail>
		<title>Blaster Slam Razor</title>
		<creator>Handsome Jeffrey Aardvark</creator>
		<relatedgames />
	</game>
	<game id="10952604" rating="0" difficulty="0" status="0" timeToBeat="0" createDate="09/21/2009">
		<thumbnail>/gamecreators/images2/Obvious/Megan/Octopus/10952604.jpg</thumbnail>
		<title>Escape Thunder Defense</title>
		<creator>Obvious Megan Octopus</creator>
		<relatedgames />
	</game>
	<game id="17560703" rating="0" difficulty="0" status="0" timeToBeat="0" createDate="09/20/2012">
		<thumbnail>/gamecreators/images2/Volcanic/Veronica/Splat/17560703.jpg</thumbnail>
		<title>Mega Rocket Chase</title>
		<creator>Volcanic Veronica Splat</creator>
		<relatedgames />
	</game>
	<game id="17309781" rating="0" difficulty="0" status="0" timeToBeat="0" createDate="08/06/2012">
		<thumbnail>/gamecreators/images2/Pleasant/Alan/Gamer/17309781.jpg</thumbnail>
		<title>Razor Jetray Laser</title>
		<creator>Pleasant Alan Gamer</creator>
		<relatedgames />
	</game>
	<game id="10918912" rating="0" difficulty="0" status="0" timeToBeat="0" createDate="09/18/2009">
		<thumbnail>/gamecreators/images2/Strange/Daniel/Squid/10918912.jpg</thumbnail>
		<title>Doom Chase Space</title>
		<creator>Strange Daniel Squid</creator>
		<relatedgames />
	</game>
	<game id="10931159" rating="0" difficulty="0" status="0" timeToBeat="0" createDate="09/19/2009">
		<thumbnail>/gamecreators/images2/Chilly/Eddie/Fiddle/10931159.jpg</thumbnail>
		<title>Alien Ambush Defense</title>
		<creator>Chilly Eddie Fiddle</creator>
		<relatedgames />
	</game>
	<game id="10039272" rating="0" difficulty="0" status="0">
		<thumbnail>/gamecreators/images/Loud/Steven/Charger/10039272.jpg</thumbnail>
		<title>Power Metal Attack</title>
		<creator>Loud Steven Charger</creator>
		<relatedgames />
	</game>
	<game id="10924853" rating="0" difficulty="0" status="0" timeToBeat="0" createDate="09/19/2009">
		<thumbnail>/gamecreators/images2/Enormous/Brandon/Vector/10924853.jpg</thumbnail>
		<title>Solar Ultimate Fury</title>
		<creator>Enormous Brandon Vector</creator>
		<relatedgames />
	</game>
	<game id="10952581" rating="0" difficulty="0" status="0" timeToBeat="0" createDate="09/21/2009">
		<thumbnail>/gamecreators/images2/Gloomy/Harry/Bolt/10952581.jpg</thumbnail>
		<title>Danger Vilgax Fusion</title>
		<creator>Gloomy Harry Bolt</creator>
		<relatedgames />
	</game>
</cartoonnetwork>