<cartoonnetwork>
	<response status="SUCCESS"/>
	<game id="17389024" rating="0" difficulty="0" status="0" timeToBeat="0" createDate="09/02/2012">
		<thumbnail>
			http://i.cdn.turner.com/v5cache/CARTOON/gamecreator/images2/Puzzling/Zachary/Thorax/17389024.jpg
		</thumbnail>
		<title>Doom Sonic Vilgax</title>
		<creator>Puzzling Zachary Thorax</creator>
		<relatedgames/>
	</game>
	<game id="16993778" rating="0" difficulty="0" status="0" timeToBeat="0" createDate="05/04/2012">
		<thumbnail>
			http://i.cdn.turner.com/v5cache/CARTOON/gamecreator/images2/Baroness/Anna/Beast/16993778.jpg
		</thumbnail>
		<title>Animo Patrol Steel</title>
		<creator>Baroness Anna Beast</creator>
		<relatedgames/>
	</game>
	<game id="17295706" rating="0" difficulty="0" status="0" timeToBeat="0" createDate="08/02/2012">
		<thumbnail>
			http://i.cdn.turner.com/v5cache/CARTOON/gamecreator/images2/Electric/Rudolph/Soldier/17295706.jpg
		</thumbnail>
		<title>Iron Hero Fury</title>
		<creator>Electric Rudolph Soldier</creator>
		<relatedgames/>
	</game>
	<game id="10925864" rating="0" difficulty="0" status="0" timeToBeat="0" createDate="09/19/2009">
		<thumbnail>
			http://i.cdn.turner.com/v5cache/CARTOON/gamecreator/images2/Wacky/Jack/Virtuoso/10925864.jpg
		</thumbnail>
		<title>Turbo Techno Laser</title>
		<creator>Wacky Jack Virtuoso</creator>
		<relatedgames/>
	</game>
	<game id="16956383" rating="0" difficulty="0" status="0" timeToBeat="0" createDate="04/22/2012">
		<thumbnail>
			http://i.cdn.turner.com/v5cache/CARTOON/gamecreator/images2/Capable/Bugsy/Sword/16956383.jpg
		</thumbnail>
		<title>Rush Ultimate Titan</title>
		<creator>Capable Bugsy Sword</creator>
		<relatedgames/>
	</game>
	<game id="16965108" rating="0" difficulty="0" status="0" timeToBeat="0" createDate="04/24/2012">
		<thumbnail>
			http://i.cdn.turner.com/v5cache/CARTOON/gamecreator/images2/Feral/Andrew/Mustang/16965108.jpg
		</thumbnail>
		<title>Titan Hyper Breaker</title>
		<creator>Feral Andrew Mustang</creator>
		<relatedgames/>
	</game>
	<game id="10950785" rating="0" difficulty="0" status="0" timeToBeat="0" createDate="09/20/2009">
		<thumbnail>
			http://i.cdn.turner.com/v5cache/CARTOON/gamecreator/images2/Fragrant/Dudley/Fritter/10950785.jpg
		</thumbnail>
		<title>Laser Rocket Streak</title>
		<creator>Fragrant Dudley Fritter</creator>
		<relatedgames/>
	</game>
	<game id="17387691" rating="0" difficulty="0" status="0" timeToBeat="0" createDate="09/02/2012">
		<thumbnail>
			http://i.cdn.turner.com/v5cache/CARTOON/gamecreator/images2/Loyal/Juan/Parallax/17387691.jpg
		</thumbnail>
		<title>Cannonbolt Metal Mission</title>
		<creator>Loyal Juan Parallax</creator>
		<relatedgames/>
	</game>
	<game id="17276635" rating="0" difficulty="0" status="0" timeToBeat="0" createDate="07/29/2012">
		<thumbnail>
			http://i.cdn.turner.com/v5cache/CARTOON/gamecreator/images2/Roy/Razor/17276635.jpg
		</thumbnail>
		<title>Echo Magno Ultra</title>
		<creator>Roy Razor</creator>
		<relatedgames/>
	</game>
	<game id="17560703" rating="0" difficulty="0" status="0" timeToBeat="0" createDate="09/20/2012">
		<thumbnail>
			http://i.cdn.turner.com/v5cache/CARTOON/gamecreator/images2/Volcanic/Veronica/Splat/17560703.jpg
		</thumbnail>
		<title>Mega Rocket Chase</title>
		<creator>Volcanic Veronica Splat</creator>
		<relatedgames/>
	</game>
</cartoonnetwork>