<?xml version='1.0' encoding='utf-8'?>
<cartoonnetwork>
	<response status="SUCCESS" />
	<game id="10786623" rating="0" difficulty="0" status="0" timeToBeat="0" createDate="09/02/2009">
		<thumbnail>/gamecreators/images2/Hardy/Adam/Fossil/10786623.jpg</thumbnail>
		<title>Hyper Adventure Rustbucket</title>
		<creator>Hardy Adam Fossil</creator>
		<relatedgames />
	</game>
	<game id="10949020" rating="0" difficulty="0" status="0" timeToBeat="0" createDate="09/20/2009">
		<thumbnail>/gamecreators/images2/Odd/Sean/Mustang/10949020.jpg</thumbnail>
		<title>Nano Giga Ambush</title>
		<creator>Odd Sean Mustang</creator>
		<relatedgames />
	</game>
	<game id="17389018" rating="0" difficulty="0" status="0" timeToBeat="0" createDate="09/02/2012">
		<thumbnail>/gamecreators/images2/Stunning/Sid/Hambone/17389018.jpg</thumbnail>
		<title>Adventure Rescue Slam</title>
		<creator>Stunning Sid Hambone</creator>
		<relatedgames />
	</game>
	<game id="17314558" rating="0" difficulty="0" status="0" timeToBeat="0" createDate="08/07/2012">
		<thumbnail>/gamecreators/images2/Yelping/Albert/Anvil/17314558.jpg</thumbnail>
		<title>Slam Patrol Slam</title>
		<creator>Yelping Albert Anvil</creator>
		<relatedgames />
	</game>
	<game id="10948852" rating="0" difficulty="0" status="0" timeToBeat="0" createDate="09/20/2009">
		<thumbnail>/gamecreators/images2/Chilly/Zoe/Wizard/10948852.jpg</thumbnail>
		<title>Warrior Warrior Warrior</title>
		<creator>Chilly Zoe Wizard</creator>
		<relatedgames />
	</game>
	<game id="10923848" rating="0" difficulty="0" status="0" timeToBeat="0" createDate="09/19/2009">
		<thumbnail>/gamecreators/images2/Lucky/Egbert/Avocado/10923848.jpg</thumbnail>
		<title>Alien Adventure Ambush</title>
		<creator>Lucky Egbert Avocado</creator>
		<relatedgames />
	</game>
	<game id="16875573" rating="0" difficulty="0" status="0" timeToBeat="0" createDate="04/02/2012">
		<thumbnail>/gamecreators/images2/Honest/Jose/Kungfu/16875573.jpg</thumbnail>
		<title>Laser Big Space</title>
		<creator>Honest Jose Kungfu</creator>
		<relatedgames />
	</game>
	<game id="17550908" rating="0" difficulty="0" status="0" timeToBeat="0" createDate="09/20/2012">
		<thumbnail>/gamecreators/images2/Pleasant/Leah/Jinx/17550908.jpg</thumbnail>
		<title>Assault Attack Robot</title>
		<creator>Pleasant Leah Jinx</creator>
		<relatedgames />
	</game>
	<game id="17386673" rating="0" difficulty="0" status="0" timeToBeat="0" createDate="09/01/2012">
		<thumbnail>/gamecreators/images2/Strong/Chris/Eel/17386673.jpg</thumbnail>
		<title>Plasma Mission Escape</title>
		<creator>Strong Chris Eel</creator>
		<relatedgames />
	</game>
	<game id="17334355" rating="0" difficulty="0" status="0" timeToBeat="0" createDate="08/13/2012">
		<thumbnail>/gamecreators/images2/Wondrous/Scooby/Creature/17334355.jpg</thumbnail>
		<title>Alien Dark Ultimate</title>
		<creator>Wondrous Scooby Creature</creator>
		<relatedgames />
	</game>
</cartoonnetwork>