<?xml version='1.0' encoding='utf-8'?>
<cartoonnetwork>
	<response status="SUCCESS" />
	<game id="17148915" rating="0" difficulty="0" status="0" timeToBeat="0" createDate="06/22/2012">
		<thumbnail>/gamecreators/images2/Creative/Fred/Robot/17148915.jpg</thumbnail>
		<title>Alien Ambush Challenge</title>
		<creator>Creative Fred Robot</creator>
		<relatedgames />
	</game>
	<game id="17418896" rating="0" difficulty="0" status="0" timeToBeat="0" createDate="09/16/2012">
		<thumbnail>/gamecreators/images2/Quantum/Scarlett/Nebula/17418896.jpg</thumbnail>
		<title>Space Space Space</title>
		<creator>Quantum Scarlett Nebula</creator>
		<relatedgames />
	</game>
	<game id="17359324" rating="0" difficulty="0" status="0" timeToBeat="0" createDate="08/22/2012">
		<thumbnail>/gamecreators/images2/Crazy/Andy/Turbo/17359324.jpg</thumbnail>
		<title>Streak Drone Adventure</title>
		<creator>Crazy Andy Turbo</creator>
		<relatedgames />
	</game>
	<game id="17361579" rating="0" difficulty="0" status="0" timeToBeat="0" createDate="08/23/2012">
		<thumbnail>/gamecreators/images2/Ultimate/Waldo/Firefly/17361579.jpg</thumbnail>
		<title>Cosmic Adventure Sonic</title>
		<creator>Ultimate Waldo Firefly</creator>
		<relatedgames />
	</game>
	<game id="10921299" rating="0" difficulty="0" status="0" timeToBeat="0" createDate="09/18/2009">
		<thumbnail>/gamecreators/images2/Dainty/Rachel/Ladybug/10921299.jpg</thumbnail>
		<title>Rumble Chase Assault</title>
		<creator>Dainty Rachel Ladybug</creator>
		<relatedgames />
	</game>
	<game id="16935535" rating="0" difficulty="0" status="0" timeToBeat="0" createDate="04/15/2012">
		<thumbnail>/gamecreators/images2/Gorgeous/Earl/Shuriken/16935535.jpg</thumbnail>
		<title>Vilgax Beast Rescue</title>
		<creator>Gorgeous Earl Shuriken</creator>
		<relatedgames />
	</game>
	<game id="17200966" rating="0" difficulty="0" status="0" timeToBeat="0" createDate="07/08/2012">
		<thumbnail>/gamecreators/images2/Sloppy/Ronald/Tundra/17200966.jpg</thumbnail>
		<title>Cannonbolt Spark Metal</title>
		<creator>Sloppy Ronald Tundra</creator>
		<relatedgames />
	</game>
	<game id="17288662" rating="0" difficulty="0" status="0" timeToBeat="0" createDate="08/01/2012">
		<thumbnail>/gamecreators/images2/Rancid/Chester/Magician/17288662.jpg</thumbnail>
		<title>Titan Alien Nano</title>
		<creator>Rancid Chester Magician</creator>
		<relatedgames />
	</game>
	<game id="10050014" rating="0" difficulty="0" status="0">
		<thumbnail>/gamecreators/images/Alien/Hazel/Fishbowl/10050014.jpg</thumbnail>
		<title>Ultimate Adventure Ambush</title>
		<creator>Alien Hazel Fishbowl</creator>
		<relatedgames />
	</game>
	<game id="17404696" rating="0" difficulty="0" status="0" timeToBeat="0" createDate="09/09/2012">
		<thumbnail>/gamecreators/images2/Golden/Benjamin/Hedgehog/17404696.jpg</thumbnail>
		<title>Robot Hyper Mission</title>
		<creator>Golden Benjamin Hedgehog</creator>
		<relatedgames />
	</game>
</cartoonnetwork>