<?xml version='1.0' encoding='utf-8'?>
<cartoonnetwork>
	<response status="SUCCESS" />
	<game id="16900941" rating="0" difficulty="0" status="0" timeToBeat="0" createDate="04/08/2012">
		<thumbnail>/gamecreators/images2/Comical/Ariana/Brine/16900941.jpg</thumbnail>
		<title>Rocket Quake Smash</title>
		<creator>Comical Ariana Brine</creator>
		<relatedgames />
	</game>
	<game id="10918878" rating="0" difficulty="0" status="0" timeToBeat="0" createDate="09/18/2009">
		<thumbnail>/gamecreators/images2/Majestic/Adam/Bolt/10918878.jpg</thumbnail>
		<title>Blaster Ambush Assault</title>
		<creator>Majestic Adam Bolt</creator>
		<relatedgames />
	</game>
	<game id="17244101" rating="0" difficulty="0" status="0" timeToBeat="0" createDate="07/20/2012">
		<thumbnail>/gamecreators/images2/Prince/Dan/Galaxy/17244101.jpg</thumbnail>
		<title>Ultimate Quake Mission</title>
		<creator>Prince Dan Galaxy</creator>
		<relatedgames />
	</game>
	<game id="10920479" rating="0" difficulty="0" status="0" timeToBeat="0" createDate="09/18/2009">
		<thumbnail>/gamecreators/images2/Colossal/Joey/Wizard/10920479.jpg</thumbnail>
		<title>Rocket Clash Battle</title>
		<creator>Colossal Joey Wizard</creator>
		<relatedgames />
	</game>
	<game id="17133581" rating="0" difficulty="0" status="0" timeToBeat="0" createDate="06/17/2012">
		<thumbnail>/gamecreators/images2/Titanic/Clyde/Dwarf/17133581.jpg</thumbnail>
		<title>Adventure Smash Burst</title>
		<creator>Titanic Clyde Dwarf</creator>
		<relatedgames />
	</game>
	<game id="17549943" rating="0" difficulty="0" status="0" timeToBeat="0" createDate="09/20/2012">
		<thumbnail>/gamecreators/images2/Electric/David/Gamer/17549943.jpg</thumbnail>
		<title>Chill Shock Force</title>
		<creator>Electric David Gamer</creator>
		<relatedgames />
	</game>
	<game id="10931081" rating="0" difficulty="0" status="0" timeToBeat="0" createDate="09/19/2009">
		<thumbnail>/gamecreators/images2/Cranky/Jake/Bamboo/10931081.jpg</thumbnail>
		<title>Vilgax Smash Invasion</title>
		<creator>Cranky Jake Bamboo</creator>
		<relatedgames />
	</game>
	<game id="17338691" rating="0" difficulty="0" status="0" timeToBeat="0" createDate="08/14/2012">
		<thumbnail>/gamecreators/images2/Gentle/Clifford/Beast/17338691.jpg</thumbnail>
		<title>Ben Adventure Cosmic</title>
		<creator>Gentle Clifford Beast</creator>
		<relatedgames />
	</game>
	<game id="10930760" rating="0" difficulty="0" status="0" timeToBeat="0" createDate="09/19/2009">
		<thumbnail>/gamecreators/images2/Shrewd/Mia/Wombat/10930760.jpg</thumbnail>
		<title>Invasion Earth Magno</title>
		<creator>Shrewd Mia Wombat</creator>
		<relatedgames />
	</game>
	<game id="10927951" rating="0" difficulty="0" status="0" timeToBeat="0" createDate="09/19/2009">
		<thumbnail>/gamecreators/images2/Feisty/Pearl/Hambone/10927951.jpg</thumbnail>
		<title>Turbo Alien Adventure</title>
		<creator>Feisty Pearl Hambone</creator>
		<relatedgames />
	</game>
</cartoonnetwork>