<cartoonnetwork>
	<response status="SUCCESS"/>
	<game id="17331653" rating="0" difficulty="0" status="0" timeToBeat="0" createDate="08/12/2012">
		<thumbnail>
			http://i.cdn.turner.com/v5cache/CARTOON/gamecreator/images2/Electric/Izzy/Coconut/17331653.jpg
		</thumbnail>
		<title>Energy Whirlwind Cosmic</title>
		<creator>Electric Izzy Coconut</creator>
		<relatedgames/>
	</game>
	<game id="16947501" rating="0" difficulty="0" status="0" timeToBeat="0" createDate="04/20/2012">
		<thumbnail>
			http://i.cdn.turner.com/v5cache/CARTOON/gamecreator/images2/Gentle/Rosetta/Snowball/16947501.jpg
		</thumbnail>
		<title>Ultimate Brainstorm Vilgax</title>
		<creator>Gentle Rosetta Snowball</creator>
		<relatedgames/>
	</game>
	<game id="10056467" rating="0" difficulty="0" status="0">
		<thumbnail>
			http://i.cdn.turner.com/v5cache/CARTOON/gamecreator/images/Mirthful/Danielle/Monster/10056467.jpg
		</thumbnail>
		<title>Storm Ultimate Fusion</title>
		<creator>Mirthful Danielle Monster</creator>
		<relatedgames/>
	</game>
	<game id="17311257" rating="0" difficulty="0" status="0" timeToBeat="0" createDate="08/06/2012">
		<thumbnail>
			http://i.cdn.turner.com/v5cache/CARTOON/gamecreator/images2/Epic/Igor/Minotaur/17311257.jpg
		</thumbnail>
		<title>Adventure Sonic Fury</title>
		<creator>Epic Igor Minotaur</creator>
		<relatedgames/>
	</game>
	<game id="17363601" rating="0" difficulty="0" status="0" timeToBeat="0" createDate="08/24/2012">
		<thumbnail>
			http://i.cdn.turner.com/v5cache/CARTOON/gamecreator/images2/Icy/Bridget/Atlas/17363601.jpg
		</thumbnail>
		<title>Metal Spidermonkey Spidermonkey</title>
		<creator>Icy Bridget Atlas</creator>
		<relatedgames/>
	</game>
	<game id="10920168" rating="0" difficulty="0" status="0" timeToBeat="0" createDate="09/18/2009">
		<thumbnail>
			http://i.cdn.turner.com/v5cache/CARTOON/gamecreator/images2/Ticklish/Spike/Dynamite/10920168.jpg
		</thumbnail>
		<title>Cosmic Fire Slam</title>
		<creator>Ticklish Spike Dynamite</creator>
		<relatedgames/>
	</game>
	<game id="17539932" rating="0" difficulty="0" status="0" timeToBeat="0" createDate="09/20/2012">
		<thumbnail>
			http://i.cdn.turner.com/v5cache/CARTOON/gamecreator/images2/Nervous/Ben/Burst/17539932.jpg
		</thumbnail>
		<title>Terraspin Whirlwind Turbo</title>
		<creator>Nervous Ben Burst</creator>
		<relatedgames/>
	</game>
	<game id="17389747" rating="0" difficulty="0" status="0" timeToBeat="0" createDate="09/02/2012">
		<thumbnail>
			http://i.cdn.turner.com/v5cache/CARTOON/gamecreator/images2/Sleepy/William/Tiger/17389747.jpg
		</thumbnail>
		<title>Attack Mission Big</title>
		<creator>Sleepy William Tiger</creator>
		<relatedgames/>
	</game>
	<game id="17333152" rating="0" difficulty="0" status="0" timeToBeat="0" createDate="08/12/2012">
		<thumbnail>
			http://i.cdn.turner.com/v5cache/CARTOON/gamecreator/images2/Academic/Edward/Cowboy/17333152.jpg
		</thumbnail>
		<title>Ultimate Cannonbolt Rush</title>
		<creator>Academic Edward Cowboy</creator>
		<relatedgames/>
	</game>
	<game id="16944232" rating="0" difficulty="0" status="0" timeToBeat="0" createDate="04/18/2012">
		<thumbnail>
			http://i.cdn.turner.com/v5cache/CARTOON/gamecreator/images2/Bogus/Calvin/Baloney/16944232.jpg
		</thumbnail>
		<title>Chill Big Assault</title>
		<creator>Bogus Calvin Baloney</creator>
		<relatedgames/>
	</game>
</cartoonnetwork>