<cartoonnetwork>
	<response status="SUCCESS"/>
	<game id="17265238" rating="0" difficulty="0" status="0" timeToBeat="0" createDate="07/25/2012">
		<thumbnail>
			http://i.cdn.turner.com/v5cache/CARTOON/gamecreator/images2/Orange/Olivia/Maestro/17265238.jpg
		</thumbnail>
		<title>Gear Vilgax Burst</title>
		<creator>Orange Olivia Maestro</creator>
		<relatedgames/>
	</game>
	<game id="10953211" rating="0" difficulty="0" status="0" timeToBeat="0" createDate="09/21/2009">
		<thumbnail>
			http://i.cdn.turner.com/v5cache/CARTOON/gamecreator/images2/Artistic/Alan/Stampede/10953211.jpg
		</thumbnail>
		<title>Droid Crusher Invasion</title>
		<creator>Artistic Alan Stampede</creator>
		<relatedgames/>
	</game>
	<game id="10055993" rating="0" difficulty="0" status="0">
		<thumbnail>
			http://i.cdn.turner.com/v5cache/CARTOON/gamecreator/images/Scary/Leonardo/Droid/10055993.jpg
		</thumbnail>
		<title>Earth Alien Adventure</title>
		<creator>Scary Leonardo Droid</creator>
		<relatedgames/>
	</game>
	<game id="10043501" rating="0" difficulty="0" status="0">
		<thumbnail>
			http://i.cdn.turner.com/v5cache/CARTOON/gamecreator/images/Wily/Jackson/Umbrella/10043501.jpg
		</thumbnail>
		<title>Alien Blaster Adventure</title>
		<creator>Wily Jackson Umbrella</creator>
		<relatedgames/>
	</game>
	<game id="10930994" rating="0" difficulty="0" status="0" timeToBeat="0" createDate="09/19/2009">
		<thumbnail>
			http://i.cdn.turner.com/v5cache/CARTOON/gamecreator/images2/Fizzy/Casey/Flipper/10930994.jpg
		</thumbnail>
		<title>Fire Fire Warrior</title>
		<creator>Fizzy Casey Flipper</creator>
		<relatedgames/>
	</game>
	<game id="17323636" rating="0" difficulty="0" status="0" timeToBeat="0" createDate="08/10/2012">
		<thumbnail>
			http://i.cdn.turner.com/v5cache/CARTOON/gamecreator/images2/Drowzy/Yancy/Porridge/17323636.jpg
		</thumbnail>
		<title>Rocket Hex Drone</title>
		<creator>Drowzy Yancy Porridge</creator>
		<relatedgames/>
	</game>
	<game id="17419559" rating="0" difficulty="0" status="0" timeToBeat="0" createDate="09/16/2012">
		<thumbnail>
			http://i.cdn.turner.com/v5cache/CARTOON/gamecreator/images2/Friendly/Felix/Dodo/17419559.jpg
		</thumbnail>
		<title>Stone Hero Laser</title>
		<creator>Friendly Felix Dodo</creator>
		<relatedgames/>
	</game>
	<game id="10038852" rating="0" difficulty="0" status="0">
		<thumbnail>
			http://i.cdn.turner.com/v5cache/CARTOON/gamecreator/images/Magnetic/Alan/Blubber/10038852.jpg
		</thumbnail>
		<title>Shock Spark Invasion</title>
		<creator>Magnetic Alan Blubber</creator>
		<relatedgames/>
	</game>
	<game id="10934766" rating="0" difficulty="0" status="0" timeToBeat="0" createDate="09/19/2009">
		<thumbnail>
			http://i.cdn.turner.com/v5cache/CARTOON/gamecreator/images2/Savage/Jacob/Pulse/10934766.jpg
		</thumbnail>
		<title>Nova Assault Earth</title>
		<creator>Savage Jacob Pulse</creator>
		<relatedgames/>
	</game>
	<game id="10945458" rating="0" difficulty="0" status="0" timeToBeat="0" createDate="09/20/2009">
		<thumbnail>
			http://i.cdn.turner.com/v5cache/CARTOON/gamecreator/images2/Atomic/Zelda/Sardine/10945458.jpg
		</thumbnail>
		<title>Sonic Alien Universe</title>
		<creator>Atomic Zelda Sardine</creator>
		<relatedgames/>
	</game>
</cartoonnetwork>