<cartoonnetwork>
	<response status="SUCCESS"/>
	<game id="17416299" rating="0" difficulty="0" status="0" timeToBeat="0" createDate="09/15/2012">
		<thumbnail>
			http://i.cdn.turner.com/v5cache/CARTOON/gamecreator/images2/Creative/Mario/Noodle/17416299.jpg
		</thumbnail>
		<title>Alien Droid Escape</title>
		<creator>Creative Mario Noodle</creator>
		<relatedgames/>
	</game>
	<game id="10654995" rating="0" difficulty="0" status="0" timeToBeat="0" createDate="08/18/2009">
		<thumbnail>
			http://i.cdn.turner.com/v5cache/CARTOON/gamecreator/images2/Brainy/Nicholas/Chimera/10654995.jpg
		</thumbnail>
		<title>Solar Invasion Rush</title>
		<creator>Brainy Nicholas Chimera</creator>
		<relatedgames/>
	</game>
	<game id="10916705" rating="0" difficulty="0" status="0" timeToBeat="0" createDate="09/18/2009">
		<thumbnail>
			http://i.cdn.turner.com/v5cache/CARTOON/gamecreator/images2/Infinite/Jill/Thorax/10916705.jpg
		</thumbnail>
		<title>Rumble Challenge Slam</title>
		<creator>Infinite Jill Thorax</creator>
		<relatedgames/>
	</game>
	<game id="17417580" rating="0" difficulty="0" status="0" timeToBeat="0" createDate="09/15/2012">
		<thumbnail>
			http://i.cdn.turner.com/v5cache/CARTOON/gamecreator/images2/Queen/Alyssa/Javelin/17417580.jpg
		</thumbnail>
		<title>Search Techno Animo</title>
		<creator>Queen Alyssa Javelin</creator>
		<relatedgames/>
	</game>
	<game id="17362230" rating="0" difficulty="0" status="0" timeToBeat="0" createDate="08/23/2012">
		<thumbnail>
			http://i.cdn.turner.com/v5cache/CARTOON/gamecreator/images2/Reckless/Igor/Cupcake/17362230.jpg
		</thumbnail>
		<title>Space Metal Assault</title>
		<creator>Reckless Igor Cupcake</creator>
		<relatedgames/>
	</game>
	<game id="10055612" rating="0" difficulty="0" status="0">
		<thumbnail>
			http://i.cdn.turner.com/v5cache/CARTOON/gamecreator/images/Uncanny/Dolly/Cyborg/10055612.jpg
		</thumbnail>
		<title>Shock Titan Adventure</title>
		<creator>Uncanny Dolly Cyborg</creator>
		<relatedgames/>
	</game>
	<game id="17292491" rating="0" difficulty="0" status="0" timeToBeat="0" createDate="08/02/2012">
		<thumbnail>
			http://i.cdn.turner.com/v5cache/CARTOON/gamecreator/images2/Dandy/Penny/Minotaur/17292491.jpg
		</thumbnail>
		<title>Clash Invasion Ultimate</title>
		<creator>Dandy Penny Minotaur</creator>
		<relatedgames/>
	</game>
	<game id="17312986" rating="0" difficulty="0" status="0" timeToBeat="0" createDate="08/07/2012">
		<thumbnail>
			http://i.cdn.turner.com/v5cache/CARTOON/gamecreator/images2/Mellow/Benjamin/Banzai/17312986.jpg
		</thumbnail>
		<title>Shadow Rock Nova</title>
		<creator>Mellow Benjamin Banzai</creator>
		<relatedgames/>
	</game>
	<game id="16989085" rating="0" difficulty="0" status="0" timeToBeat="0" createDate="05/02/2012">
		<thumbnail>
			http://i.cdn.turner.com/v5cache/CARTOON/gamecreator/images2/Shiny/Homer/Soldier/16989085.jpg
		</thumbnail>
		<title>Crusher Adventure Universe</title>
		<creator>Shiny Homer Soldier</creator>
		<relatedgames/>
	</game>
	<game id="17262083" rating="0" difficulty="0" status="0" timeToBeat="0" createDate="07/25/2012">
		<thumbnail>
			http://i.cdn.turner.com/v5cache/CARTOON/gamecreator/images2/Yucky/Rufus/Kiwi/17262083.jpg
		</thumbnail>
		<title>Invasion Spidermonkey Rock</title>
		<creator>Yucky Rufus Kiwi</creator>
		<relatedgames/>
	</game>
</cartoonnetwork>